[
  {
    "id": 1001,
    "status": "Approved"
  },
  {
    "id": 1003,
    "status": "Approved"
  },
  {
    "id": 1004,
    "status": "Rejected"
  },
  {
    "id": 1005,
    "status": "Approved"
  },
  {
    "id": 1006,
    "status": "Rejected"
  },
  {
    "id": 1008,
    "status": "Rejected"
  },
  {
    "id": 1009,
    "status": "Approved"
  },
  {
    "id": 1010,
    "status": "Approved"
  },
  {
    "id": 1011,
    "status": "Approved"
  },
  {
    "id": 1012,
    "status": "Rejected"
  },
  {
    "id": 1013,
    "status": "Approved"
  },
  {
    "id": 1014,
    "status": "Approved"
  },
  {
    "id": 1015,
    "status": "Approved"
  },
  {
    "id": 1016,
    "status": "Rejected"
  },
  {
    "id": 1017,
    "status": "Approved"
  },
  {
    "id": 1018,
    "status": "Rejected"
  },
  {
    "id": 1019,
    "status": "Approved"
  },
  {
    "id": 1020,
    "status": "Approved"
  }
]